fastposter/__init__.py
fastposter/__version__.py
fastposter/fastposter.py
fastposter-1.6.1.dist-info/LICENSE
fastposter-1.6.1.dist-info/METADATA
fastposter-1.6.1.dist-info/WHEEL
fastposter-1.6.1.dist-info/top_level.txt
fastposter-1.6.1.dist-info/RECORD
