Metadata-Version: 2.1
Name: fastposter
Version: 1.6.1
Summary: A Python client for fastposter cloud
Home-page: https://github.com/psoho/fastposter-client-python
Author: Alex
Author-email: service@fastposter.net
License: MIT License (MIT)
Project-URL: Documentation, https://fastposter.net/doc/sdk/python.html
Project-URL: Source, https://github.com/psoho/fastposter-client-python
License-File: LICENSE
Requires-Dist: requests (==2.31.0)
